[
  {
    "id": "2301001",
    "payer": "loja",
    "acess_key": "42230107432517001847550030007554411000084806",
    "emissionDate": "01/01/2023 04:01:23",
    "dueDate": "01/01/2023 04:03:45",
    "payday": "01/01/2023 04:03:45",
    "amount": "175,09",
    "status": "emitida"
  },
  {
    "id": "2301002",
    "payer": "loja",
    "acess_key": "42230107432517001847550030007554281000134542",
    "emissionDate": "01/01/2023 04:08:13",
    "dueDate": "01/01/2023 04:11:34",
    "payday": "01/01/2023 04:11:34",
    "amount": "597,34",
    "status": "emitida"
  },
  {
    "id": "2301003",
    "payer": "loja",
    "acess_key": "33230134849096000189550010000000161591173139",
    "emissionDate": "01/01/2023 04:19:00",
    "dueDate": "01/01/2023 06:49:15",
    "payday": "01/01/2023 06:49:15",
    "amount": "59570,51",
    "status": "emitida"
  },
  {
    "id": "2301004",
    "payer": "loja",
    "acess_key": "42230107432517001847550030007558911000105181",
    "emissionDate": "01/01/2023 04:22:20",
    "dueDate": "01/01/2023 04:23:15",
    "payday": "01/01/2023 04:23:15",
    "amount": "1818,78",
    "status": "emitida"
  },
  {
    "id": "2301005",
    "payer": "loja",
    "acess_key": "51230120978400000183550040000023931146944898",
    "emissionDate": "01/01/2023 04:46:48",
    "dueDate": "01/01/2023 05:46:46",
    "payday": "01/01/2023 05:46:46",
    "amount": "360,81",
    "status": "emitida"
  },
  {
    "id": "2302001",
    "payer": "loja",
    "acess_key": "35230145727558000101550010000001701005902606",
    "emissionDate": "01/02/2023 05:00:00",
    "dueDate": "05/02/2023 08:29:05",
    "payday": "04/01/2023 08:29:05",
    "amount": "6694,00",
    "status": "emitida"
  },
  {
    "id": "2302002",
    "payer": "loja",
    "acess_key": "35230145727558000101550010000001731005902608",
    "emissionDate": "01/02/2023 05:00:01",
    "dueDate": "05/02/2023 08:29:06",
    "payday": "01/01/2023 08:29:06",
    "amount": "15094,00",
    "status": "emitida"
  },
  {
    "id": "2302003",
    "payer": "loja",
    "acess_key": "35230145727558000101550010000001801005902602",
    "emissionDate": "01/02/2023 05:00:02",
    "dueDate": "05/02/2023 08:29:07",
    "payday": "01/01/2023 08:29:08",
    "amount": "4077,00",
    "status": "emitida"
  },
  {
    "id": "2302004",
    "payer": "loja",
    "acess_key": "35230145727558000101550010000001811005902600",
    "emissionDate": "01/02/2023 05:00:03",
    "dueDate": "05/02/2023 08:29:08",
    "payday": "01/01/2023 08:29:08",
    "amount": "10397,00",
    "status": "emitida"
  },
  {
    "id": "2302005",
    "payer": "loja",
    "acess_key": "33230101226416000195550010000594431584575097",
    "emissionDate": "01/02/2023 05:00:04",
    "dueDate": "05/02/2023 08:29:09",
    "payday": "02/01/2023 05:08:38",
    "amount": "4655,80",
    "status": "emitida"
  },
  {
    "id": "2303001",
    "payer": "loja",
    "acess_key": "35230141068389000194550010000003151220140003",
    "emissionDate": "01/03/2023 05:05:00",
    "dueDate": "06/03/2023 09:43:54",
    "payday": "01/03/2023 09:43:54",
    "amount": "7644,88",
    "status": "emitida"
  },
  {
    "id": "2303002",
    "payer": "loja",
    "acess_key": "33230101226416000195550010000594451565712720",
    "emissionDate": "01/03/2023 05:05:01",
    "dueDate": "06/03/2023 09:43:55",
    "payday": "01/03/2023 09:43:55",
    "amount": "4840,01",
    "status": "emitida"
  },
  {
    "id": "2303003",
    "payer": "loja",
    "acess_key": "51230124503991000193550010000291771659553706",
    "emissionDate": "01/03/2023 05:05:02",
    "dueDate": "06/03/2023 09:43:56",
    "payday": "01/03/2023 09:43:56",
    "amount": "429,99",
    "status": "emitida"
  },
  {
    "id": "2303004",
    "payer": "loja",
    "acess_key": "53230161600839000660550000001521901100232010",
    "emissionDate": "01/03/2023 05:05:03",
    "dueDate": "06/03/2023 09:43:57",
    "payday": "01/03/2023 09:43:57",
    "amount": "958,65",
    "status": "emitida"
  },
  {
    "id": "2303005",
    "payer": "loja",
    "acess_key": "53230161600839000660550000001521881100099800",
    "emissionDate": "01/03/2023 05:05:04",
    "dueDate": "06/03/2023 09:43:58",
    "payday": "01/03/2023 09:43:58",
    "amount": "15210,99",
    "status": "emitida"
  },
  {
    "id": "2304001",
    "payer": "loja",
    "acess_key": "33230134849096000189550010000000151603401830",
    "emissionDate": "01/04/2023 06:10:00",
    "dueDate": "05/04/2023 06:10:01",
    "payday": "01/04/2023 06:10:02",
    "amount": "42564,19",
    "status": "emitida"
  },
  {
    "id": "2304002",
    "payer": "loja",
    "acess_key": "33230110511650000155550010000127301000339470",
    "emissionDate": "01/04/2023 06:10:01",
    "dueDate": "05/04/2023 06:10:02",
    "payday": "01/04/2023 06:10:03",
    "amount": "4783,38",
    "status": "emitida"
  },
  {
    "id": "2304003",
    "payer": "loja",
    "acess_key": "33230134849096000189550010000000171664633573",
    "emissionDate": "01/04/2023 06:10:02",
    "dueDate": "05/04/2023 06:10:03",
    "payday": "01/04/2023 06:10:04",
    "amount": "57907,32",
    "status": "emitida"
  },
  {
    "id": "2304004",
    "payer": "loja",
    "acess_key": "33230110511650000155550010000127311000339494",
    "emissionDate": "01/04/2023 06:10:03",
    "dueDate": "05/04/2023 06:10:04",
    "payday": "01/04/2023 06:10:05",
    "amount": "598,80",
    "status": "emitida"
  },
  {
    "id": "2304005",
    "payer": "loja",
    "acess_key": "35230145727558000101550010000001771005902607",
    "emissionDate": "01/04/2023 06:10:04",
    "dueDate": "05/04/2023 06:10:05",
    "payday": "01/04/2023 06:10:06",
    "amount": "167,93",
    "status": "emitida"
  },
  {
    "id": "2305001",
    "payer": "loja",
    "acess_key": "35230145727558000101550010000001781005902604",
    "emissionDate": "01/05/2023 07:00:00",
    "dueDate": "01/05/2023 07:00:01",
    "payday": "01/05/2023 07:00:02",
    "amount": "6194,00",
    "status": "emitida"
  },
  {
    "id": "2305002",
    "payer": "loja",
    "acess_key": "51230110590296000100550020000636561010726241",
    "emissionDate": "01/05/2023 07:00:01",
    "dueDate": "01/05/2023 07:00:02",
    "payday": "01/05/2023 07:00:03",
    "amount": "507,55",
    "status": "emitida"
  },
  {
    "id": "2305003",
    "payer": "loja",
    "acess_key": "33230134849096000189550010000000181179388250",
    "emissionDate": "01/05/2023 07:00:02",
    "dueDate": "01/05/2023 07:00:03",
    "payday": "01/05/2023 07:00:04",
    "amount": "58135,08",
    "status": "emitida"
  },
  {
    "id": "2305004",
    "payer": "loja",
    "acess_key": "33230135820448000721556060000002811502545333",
    "emissionDate": "01/05/2023 07:00:03",
    "dueDate": "01/05/2023 07:00:04",
    "payday": "01/05/2023 07:00:05",
    "amount": "3544,45",
    "status": "emitida"
  },
  {
    "id": "2305005",
    "payer": "loja",
    "acess_key": "33230104312370000115550010000001911900701842",
    "emissionDate": "01/05/2023 07:00:04",
    "dueDate": "01/05/2023 07:00:05",
    "payday": "01/05/2023 07:00:06",
    "amount": "419,33",
    "status": "emitida"
  },
  {
    "id": "2306001",
    "payer": "loja",
    "acess_key": "33230104312370000115550010000001971900701846",
    "emissionDate": "01/06/2023 08:10:00",
    "dueDate": "01/06/2023 08:10:01",
    "payday": "01/06/2023 08:10:02",
    "amount": "580,10",
    "status": "emitida"
  },
  {
    "id": "2306002",
    "payer": "loja",
    "acess_key": "33230104312370000115550010000001921407070072",
    "emissionDate": "01/06/2023 08:10:01",
    "dueDate": "01/06/2023 08:10:02",
    "payday": "01/06/2023 08:10:03",
    "amount": "877,32",
    "status": "emitida"
  },
  {
    "id": "2306003",
    "payer": "loja",
    "acess_key": "33230104312370000115550010000001981407070076",
    "emissionDate": "01/06/2023 08:10:02",
    "dueDate": "01/06/2023 08:10:03",
    "payday": "01/06/2023 08:10:04",
    "amount": "1007,70",
    "status": "emitida"
  },
  {
    "id": "2306004",
    "payer": "loja",
    "acess_key": "51230110590296000100550020000636571010833355",
    "emissionDate": "01/06/2023 08:10:03",
    "dueDate": "01/06/2023 08:10:04",
    "payday": "01/06/2023 08:10:05",
    "amount": "246,23",
    "status": "emitida"
  },
  {
    "id": "2306005",
    "payer": "loja",
    "acess_key": "51230118022755000152550010000620581004056105",
    "emissionDate": "01/06/2023 08:10:04",
    "dueDate": "01/06/2023 08:10:05",
    "payday": "01/06/2023 08:10:06",
    "amount": "509,34",
    "status": "emitida"
  },
  {
    "id": "2307001",
    "payer": "loja",
    "acess_key": "51230124503991000193550010000291781829835488",
    "emissionDate": "01/07/2023 08:10:05",
    "dueDate": "01/06/2023 08:10:06",
    "payday": "01/06/2023 08:10:07",
    "amount": "277,93",
    "status": "emitida"
  },
  {
    "id": "2307002",
    "payer": "loja",
    "acess_key": "52230119703111000192550010000005631350015636",
    "emissionDate": "01/07/2023 08:47:00",
    "dueDate": "01/07/2023 08:47:01",
    "payday": "01/07/2023 08:47:02",
    "amount": "66827,70",
    "status": "emitida"
  },
  {
    "id": "2307003",
    "payer": "loja",
    "acess_key": "52230119703111000192550010000005641350015641",
    "emissionDate": "01/07/2023 08:47:01",
    "dueDate": "01/07/2023 08:47:02",
    "payday": "01/07/2023 08:47:03",
    "amount": "66827,70",
    "status": "emitida"
  },
  {
    "id": "2307004",
    "payer": "loja",
    "acess_key": "25230137430723000130550010000001271148410782",
    "emissionDate": "01/07/2023 08:47:02",
    "dueDate": "01/07/2023 08:47:03",
    "payday": "01/07/2023 08:47:04",
    "amount": "4889,70",
    "status": "emitida"
  },
  {
    "id": "2307005",
    "payer": "loja",
    "acess_key": "43230104355355000154550110000056901001801625",
    "emissionDate": "01/07/2023 08:47:03",
    "dueDate": "01/07/2023 08:47:04",
    "payday": "01/07/2023 08:47:05",
    "amount": "6398,40",
    "status": "emitida"
  },
  {
    "id": "2308001",
    "payer": "loja",
    "acess_key": "33230134849096000189550010000000191968895360",
    "emissionDate": "01/08/2023 08:47:04",
    "dueDate": "01/07/2023 08:47:05",
    "payday": "01/07/2023 08:47:06",
    "amount": "13774,76",
    "status": "emitida"
  },
  {
    "id": "2308002",
    "payer": "loja",
    "acess_key": "51230110590296000100550020000636601010929099",
    "emissionDate": "01/08/2023 09:29:09",
    "dueDate": "01/08/2023 09:29:10",
    "payday": "01/08/2023 09:29:11",
    "amount": "447,02",
    "status": "emitida"
  },
  {
    "id": "2308003",
    "payer": "loja",
    "acess_key": "32230114724626000155550010000948181862271280",
    "emissionDate": "01/08/2023 09:29:10",
    "dueDate": "01/08/2023 09:29:11",
    "payday": "01/08/2023 09:29:12",
    "amount": "262,98",
    "status": "emitida"
  },
  {
    "id": "2308004",
    "payer": "loja",
    "acess_key": "33230160619202003406550680000007611027589862",
    "emissionDate": "01/08/2023 09:29:11",
    "dueDate": "01/08/2023 09:29:12",
    "payday": "01/08/2023 09:29:13",
    "amount": "4561,20",
    "status": "emitida"
  },
  {
    "id": "2308005",
    "payer": "loja",
    "acess_key": "51230133693086000134550020000237741002658152",
    "emissionDate": "01/08/2023 09:29:12",
    "dueDate": "01/08/2023 09:29:13",
    "payday": "01/08/2023 09:29:14",
    "amount": "229,21",
    "status": "emitida"
  },
  {
    "id": "2309001",
    "payer": "loja",
    "acess_key": "35230150046291000127550010000109721094001438",
    "emissionDate": "01/09/2023 09:29:13",
    "dueDate": "01/08/2023 09:29:14",
    "payday": "01/08/2023 09:29:15",
    "amount": "499,44",
    "status": "emitida"
  },
  {
    "id": "2309002",
    "payer": "loja",
    "acess_key": "51230102896716000144550010003318791806676808",
    "emissionDate": "01/09/2023 10:22:09",
    "dueDate": "01/09/2023 10:22:10",
    "payday": "01/09/2023 10:22:11",
    "amount": "375,06",
    "status": "emitida"
  },
  {
    "id": "2309003",
    "payer": "loja",
    "acess_key": "51230107418552000163550070000211161392756565",
    "emissionDate": "01/09/2023 10:22:10",
    "dueDate": "01/09/2023 10:22:11",
    "payday": "01/09/2023 10:22:12",
    "amount": "229,64",
    "status": "emitida"
  },
  {
    "id": "2309004",
    "payer": "loja",
    "acess_key": "33230135820448000721556050000002451241793735",
    "emissionDate": "01/09/2023 10:22:11",
    "dueDate": "01/09/2023 10:22:12",
    "payday": "01/09/2023 10:22:13",
    "amount": "4138,65",
    "status": "emitida"
  },
  {
    "id": "2309005",
    "payer": "loja",
    "acess_key": "51230103189859000502550010000846611177848024",
    "emissionDate": "01/09/2023 10:22:12",
    "dueDate": "01/09/2023 10:22:13",
    "payday": "01/09/2023 10:22:14",
    "amount": "325,60",
    "status": "emitida"
  },
  {
    "id": "2310001",
    "payer": "loja",
    "acess_key": "33230160619202003406550680000007621027589860",
    "emissionDate": "01/10/2023 10:22:13",
    "dueDate": "01/09/2023 10:22:14",
    "payday": "01/09/2023 10:22:15",
    "amount": "2354,40",
    "status": "emitida"
  },
  {
    "id": "2310002",
    "payer": "loja",
    "acess_key": "51230126588921000100550020000387961011120308",
    "emissionDate": "01/10/2023 11:20:30",
    "dueDate": "01/10/2023 11:20:31",
    "payday": "01/10/2023 11:20:32",
    "amount": "335,02",
    "status": "emitida"
  },
  {
    "id": "2310003",
    "payer": "loja",
    "acess_key": "35230144333497000135550010000002311800700080",
    "emissionDate": "01/10/2023 11:20:31",
    "dueDate": "01/10/2023 11:20:32",
    "payday": "01/10/2023 11:20:33",
    "amount": "5344,00",
    "status": "emitida"
  },
  {
    "id": "2310004",
    "payer": "loja",
    "acess_key": "33230101226416000195550010000594211330404030",
    "emissionDate": "01/10/2023 11:20:32",
    "dueDate": "01/10/2023 11:20:33",
    "payday": "01/10/2023 11:20:34",
    "amount": "573,35",
    "status": "emitida"
  },
  {
    "id": "2310005",
    "payer": "loja",
    "acess_key": "33230134849096000189550010000000201904728730",
    "emissionDate": "01/10/2023 11:20:33",
    "dueDate": "01/10/2023 11:20:34",
    "payday": "01/10/2023 11:20:35",
    "amount": "21754,59",
    "status": "emitida"
  },
  {
    "id": "2311001",
    "payer": "loja",
    "acess_key": "51230126588921000100550020000388021011236410",
    "emissionDate": "01/11/2023 11:20:34",
    "dueDate": "01/10/2023 11:20:35",
    "payday": "01/10/2023 11:20:36",
    "amount": "380,01",
    "status": "emitida"
  },
  {
    "id": "2311002",
    "payer": "loja",
    "acess_key": "51230133855749000170550030000124051576578308",
    "emissionDate": "01/11/2023 11:20:35",
    "dueDate": "01/11/2023 12:45:12",
    "payday": "01/11/2023 12:45:13",
    "amount": "295,09",
    "status": "emitida"
  },
  {
    "id": "2311003",
    "payer": "loja",
    "acess_key": "31230116907746000113558900366441821605904740",
    "emissionDate": "01/11/2023 11:20:36",
    "dueDate": "01/11/2023 12:45:13",
    "payday": "01/11/2023 12:45:14",
    "amount": "296,10",
    "status": "emitida"
  },
  {
    "id": "2311004",
    "payer": "loja",
    "acess_key": "52230119703111000192550010000005651350015657",
    "emissionDate": "01/11/2023 11:20:37",
    "dueDate": "01/11/2023 12:45:14",
    "payday": "01/11/2023 12:45:15",
    "amount": "4030,35",
    "status": "emitida"
  },
  {
    "id": "2311005",
    "payer": "loja",
    "acess_key": "51230124503991000193550010000291791210901716",
    "emissionDate": "01/11/2023 11:20:38",
    "dueDate": "01/11/2023 12:45:15",
    "payday": "01/11/2023 12:45:16",
    "amount": "342,61",
    "status": "emitida"
  },
  {
    "id": "2312001",
    "payer": "loja",
    "acess_key": "52230119703111000192550010000005661350015662",
    "emissionDate": "01/12/2023 12:45:15",
    "dueDate": "01/11/2023 12:45:16",
    "payday": "01/11/2023 12:45:17",
    "amount": "57712,05",
    "status": "emitida"
  },
  {
    "id": "2312002",
    "payer": "loja",
    "acess_key": "53230190347840000622550000002810221180312902",
    "emissionDate": "01/12/2023 14:01:07",
    "dueDate": "01/12/2023 14:01:08",
    "payday": "01/12/2023 14:01:09",
    "amount": "374,50",
    "status": "emitida"
  },
  {
    "id": "2312003",
    "payer": "loja",
    "acess_key": "14230133453598002924550010000122531380991174",
    "emissionDate": "01/12/2023 14:01:08",
    "dueDate": "01/12/2023 14:01:09",
    "payday": "01/12/2023 14:01:10",
    "amount": "64887,65",
    "status": "emitida"
  },
  {
    "id": "2312004",
    "payer": "loja",
    "acess_key": "53230133372251010038550090000150981321388232",
    "emissionDate": "01/12/2023 14:01:09",
    "dueDate": "01/12/2023 14:01:10",
    "payday": "01/12/2023 14:01:11",
    "amount": "101442,35",
    "status": "emitida"
  },
  {
    "id": "2312005",
    "payer": "loja",
    "acess_key": "51230123891404000118550110000096941086520820",
    "emissionDate": "01/12/2023 14:01:10",
    "dueDate": "01/12/2023 14:01:11",
    "payday": "01/12/2023 14:01:12",
    "amount": "360,15",
    "status": "emitida"
  },
  {
    "id": "23",
    "payer": "loja",
    "acess_key": "43230187958674000181558900446122371059787814",
    "emissionDate": "01/01/2023 14:01:11",
    "dueDate": "01/12/2023 14:01:12",
    "payday": "01/12/2023 14:01:13",
    "amount": "330,00",
    "status": "emitida"
  },
  {
    "id": "23",
    "payer": "loja",
    "acess_key": "43230187958674000181558900446122381489698679",
    "emissionDate": "01/01/2023 14:21:00",
    "dueDate": "01/01/2023 14:24:19",
    "payday": "01/01/2023 14:24:19",
    "amount": "330,00",
    "status": "emitida"
  },
  {
    "id": "23",
    "payer": "loja",
    "acess_key": "33230134849096000189550010000000211705876125",
    "emissionDate": "01/01/2023 14:38:00",
    "dueDate": "01/01/2023 16:37:53",
    "payday": "01/01/2023 16:37:53",
    "amount": "48086,44",
    "status": "emitida"
  },
  {
    "id": "23",
    "payer": "loja",
    "acess_key": "53230121793208000185550010000033641063148265",
    "emissionDate": "01/01/2023 15:00:01",
    "dueDate": "01/01/2023 15:40:04",
    "payday": "01/01/2023 15:40:04",
    "amount": "4008,07",
    "status": "emitida"
  }
]